{
  "08e6b314-b31c-4b45-b310-84c6da00e72d": {
    "preview": {
      "title": "Politics Survey",
      "pages": [
        [
          "6dfd3c7d-24a0-4db8-b66a-5f5f7bad1321",
          "c2d81a07-b222-4f46-beb7-af6e47f1e1c4",
          "812658ba-73d7-42ce-a867-6336faee79fa"
        ]
      ]
    },
    "published": {
      "title": "Political Survey",
      "pages": [[]]
    }
  },
  "325a91f7-d55d-4983-8f2b-76ffd86c33b8": {
    "preview": {
      "title": "Saturday Party RSVP",
      "pages": []
    },
    "published": {
      "title": "Party RSVP",
      "pages": []
    }
  },
  "64444c7a-2740-4ad5-8378-3522cef2b54d": {
    "preview": {
      "title": "Social Experiment",
      "pages": []
    },
    "published": {
      "title": "Social Experiment",
      "pages": []
    }
  },
  "59a0bb16-60cb-4f9b-a01c-fa4682d2f601": {
    "preview": {
      "title": "Customer Satisfaction Survey",
      "pages": []
    },
    "published": {
      "title": "How Was Your Stay at Out Place?",
      "pages": []
    }
  },
  "f0fabb92-1784-4763-832a-dd6ea2a96c6c": {
    "preview": {
      "title": "Event Feedback",
      "pages": []
    },
    "published": {
      "title": "Conference Feedback",
      "pages": []
    }
  },
  "ab83803c-ec3d-4526-bf9a-f6cd83a5c92e": {
    "preview": {
      "title": "Employee Engagement",
      "pages": []
    },
    "published": {
      "title": "Employee Satisfaction",
      "pages": []
    }
  },
  "52668bec-6622-4477-b94e-44da05d8f8f3": {
    "preview": {
      "title": "Team Performance",
      "pages": []
    },
    "published": {
      "title": "Team Performance",
      "pages": []
    }
  },
  "ee96350e-bce7-4a02-9eb0-acef1b4c037c": {
    "preview": {
      "title": "Rob and Leah's Vacation",
      "pages": []
    },
    "published": {
      "title": "Leah and Rob's Vacation",
      "pages": []
    }
  },
  "0a9f681e-5046-4c58-8b04-80782ef15950": {
    "preview": {
      "title": "Logo Testing",
      "pages": []
    },
    "published": {
      "title": "Logo Testing",
      "pages": []
    }
  },
  "8a4571e8-7c47-4368-b7b1-9cd8c9b4292e": {
    "preview": {
      "title": "New Hire Onboarding",
      "pages": []
    },
    "published": {
      "title": "Fresh Recruit Onboarding",
      "pages": []
    }
  },
  "c0b2a5cf-c99f-4fc3-ad3c-027ea290080d": {
    "preview": {
      "title": "University Faculty Satisfaction",
      "pages": []
    },
    "published": {
      "title": "University Faculty Satisfaction",
      "pages": []
    }
  },
  "2c69b6b3-ae49-47fb-b275-63ad6ceab92c": {
    "preview": {
      "title": "Donation Form",
      "pages": []
    },
    "published": {
      "title": "Donor Endowment Survey",
      "pages": []
    }
  },
  "8789cd1c-af0b-4e78-b86b-5105e9823d2e": {
    "preview": {
      "title": "Zodiac Sign Quiz",
      "pages": []
    },
    "published": {
      "title": "What Your Zodiac Sign Says About You",
      "pages": []
    }
  }
}
